lastcron/__init__.py
lastcron/__main__.py
lastcron/api_client.py
lastcron/async_api_client.py
lastcron/client.py
lastcron/flow.py
lastcron/logger.py
lastcron/py.typed
lastcron/types.py
lastcron/utils.py
lastcron-0.1.0.dist-info/licenses/LICENSE
lastcron-0.1.0.dist-info/METADATA
lastcron-0.1.0.dist-info/WHEEL
lastcron-0.1.0.dist-info/top_level.txt
lastcron-0.1.0.dist-info/RECORD
