Metadata-Version: 2.4
Name: lastcron
Version: 0.1.0
Summary: Python SDK for building and orchestrating workflows with LastCron
Author-email: AllanBR Creations <allan@allanbr.net>
Maintainer-email: AllanBR Creations <allan@allanbr.net>
License: Elastic-2.0
Project-URL: Homepage, https://github.com/allanbru/lastcron-sdk
Project-URL: Documentation, https://github.com/allanbru/lastcron-sdk#readme
Project-URL: Repository, https://github.com/allanbru/lastcron-sdk
Project-URL: Issues, https://github.com/allanbru/lastcron-sdk/issues
Project-URL: Changelog, https://github.com/allanbru/lastcron-sdk/releases
Keywords: orchestration,workflow,cron,task-management,automation,scheduling,data-pipeline,etl
Classifier: Development Status :: 4 - Beta
Classifier: Intended Audience :: Developers
Classifier: Topic :: Software Development :: Libraries :: Python Modules
Classifier: Topic :: System :: Monitoring
Classifier: Topic :: System :: Distributed Computing
Classifier: Programming Language :: Python :: 3
Classifier: Programming Language :: Python :: 3.8
Classifier: Programming Language :: Python :: 3.9
Classifier: Programming Language :: Python :: 3.10
Classifier: Programming Language :: Python :: 3.11
Classifier: Programming Language :: Python :: 3.12
Classifier: Operating System :: OS Independent
Classifier: Typing :: Typed
Requires-Python: >=3.8
License-File: LICENSE
Requires-Dist: requests>=2.28.0
Requires-Dist: aiohttp>=3.8.3
Provides-Extra: dev
Requires-Dist: pytest>=7.0.0; extra == "dev"
Requires-Dist: pytest-asyncio>=0.21.0; extra == "dev"
Requires-Dist: pytest-cov>=4.0.0; extra == "dev"
Requires-Dist: black>=23.0.0; extra == "dev"
Requires-Dist: mypy>=1.0.0; extra == "dev"
Requires-Dist: ruff>=0.1.0; extra == "dev"
Requires-Dist: types-requests>=2.28.0; extra == "dev"
Dynamic: license-file
